.codecov.yml
.dockerignore
.flake8
.pylintrc
.readthedocs.yml
.renovaterc.json
AUTHORS
CONTRIBUTING.rst
ChangeLog
Dockerfile.faucet
Dockerfile.fuzz-config
Dockerfile.fuzz-packet
Dockerfile.gauge
Dockerfile.tests
LICENSE
Makefile
README.rst
codecheck-requirements.txt
docker-compose.yaml
fuzz-requirements.txt
helper-funcs
hw_switch_config.yaml
pyrightconfig.json
requirements.txt
setup.cfg
setup.py
test-requirements.txt
.github/dependabot.yml
.github/renovate.json
.github/workflows/release-docker.yml
.github/workflows/release-python.yml
.github/workflows/tests-codecheck.yml
.github/workflows/tests-docs.yml
.github/workflows/tests-integration.yml
.github/workflows/tests-unit.yml
.github/workflows/tests-yaml-lint.yml
.github/workflows/disabled/periodic.yml
.github/workflows/disabled/release-debian.yml
adapters/README.rst
c65faucet.egg-info/PKG-INFO
c65faucet.egg-info/SOURCES.txt
c65faucet.egg-info/dependency_links.txt
c65faucet.egg-info/entry_points.txt
c65faucet.egg-info/not-zip-safe
c65faucet.egg-info/pbr.json
c65faucet.egg-info/requires.txt
c65faucet.egg-info/top_level.txt
clib/__init__.py
clib/clib_mininet_test.py
clib/clib_mininet_test_main.py
clib/clib_mininet_tests.py
clib/config_generator.py
clib/docker_host.py
clib/fakeoftable.py
clib/mininet_test_base.py
clib/mininet_test_base_topo.py
clib/mininet_test_topo.py
clib/mininet_test_util.py
clib/mininet_test_watcher.py
clib/tcpdump_helper.py
clib/valve_test_lib.py
debian/changelog
debian/compat
debian/control
debian/copyright
debian/faucet-all-in-one.install
debian/faucet-docs.docs
debian/faucet.default
debian/faucet.install
debian/faucet.postinst
debian/faucet.service
debian/gauge.default
debian/gauge.install
debian/gauge.postinst
debian/gauge.service
debian/rules
debian/watch
debian/source/format
docker/fuzz_config.sh
docker/fuzz_packet.sh
docker/install-faucet.sh
docker/localtest.sh
docker/pip_deps.sh
docker/retrycmd.sh
docker/runtests.sh
docker/shard_tests.sh
docs/.gitignore
docs/Makefile
docs/README.rst
docs/architecture.rst
docs/conf.py
docs/configuration.rst
docs/developer_guide.rst
docs/external_resources.rst
docs/fuzzing.rst
docs/index.rst
docs/installation.rst
docs/intro.rst
docs/monitoring.rst
docs/requirements.txt
docs/testing.rst
