Metadata-Version: 2.4
Name: c65faucet
Version: 1.0.98
Summary: Faucet is an OpenFlow controller that implements a layer 2 and layer 3 switch.
Home-page: https://faucet.nz
Author: Faucet development team
Author-email: faucetsdn@googlegroups.com
License: Apache-2
Keywords: openflow,openvswitch,ryu
Platform: any
Classifier: Development Status :: 5 - Production/Stable
Classifier: License :: OSI Approved :: Apache Software License
Classifier: Topic :: System :: Networking
Classifier: Natural Language :: English
Classifier: Programming Language :: Python
Classifier: Programming Language :: Python :: 3.10
Classifier: Programming Language :: Python :: 3.11
Classifier: Programming Language :: Python :: 3.12
Classifier: Operating System :: Unix
Requires-Python: >=3.10
License-File: LICENSE
License-File: AUTHORS
Requires-Dist: c65beka==1.0.2
Requires-Dist: c65chewie==1.0.5
Requires-Dist: ncclient
Requires-Dist: eventlet>=0.34.3
Requires-Dist: networkx>=1.9
Requires-Dist: pbr>=1.9
Requires-Dist: prometheus_client==0.24.1
Requires-Dist: ruamel.yaml==0.19.1
Requires-Dist: os_ken==3.1.1
Requires-Dist: pytricia>=1.0.0
Dynamic: author
Dynamic: author-email
Dynamic: classifier
Dynamic: home-page
Dynamic: keywords
Dynamic: license
Dynamic: license-file
Dynamic: platform
Dynamic: requires-dist
Dynamic: requires-python
Dynamic: summary
